pubsub_split/__init__.py
pubsub_split/split.py
tests/__init__.py
tests/test_split.py
pubsub_split-0.1.0.dist-info/LICENSE
pubsub_split-0.1.0.dist-info/METADATA
pubsub_split-0.1.0.dist-info/WHEEL
pubsub_split-0.1.0.dist-info/top_level.txt
pubsub_split-0.1.0.dist-info/zip-safe
pubsub_split-0.1.0.dist-info/RECORD
