Metadata-Version: 2.1
Name: pubsub-split
Version: 0.1.0
Summary: GCP Pubsub requires messages to be less than a certain size. This library
Requires-Dist: google-cloud-pubsub
